epilepsy2bids/__init__.py
epilepsy2bids/annotations.py
epilepsy2bids/eeg.py
epilepsy2bids/bids/convert2bids.py
epilepsy2bids/bids/events.json
epilepsy2bids/bids/chbmit/README.md
epilepsy2bids/bids/chbmit/convert2bids.py
epilepsy2bids/bids/chbmit/dataset_description.json
epilepsy2bids/bids/chbmit/eeg.json
epilepsy2bids/bids/chbmit/participants.json
epilepsy2bids/bids/seizeit/README.md
epilepsy2bids/bids/seizeit/convert2bids.py
epilepsy2bids/bids/seizeit/dataset_description.json
epilepsy2bids/bids/seizeit/eeg.json
epilepsy2bids/bids/seizeit/participants.json
epilepsy2bids/bids/siena/README.md
epilepsy2bids/bids/siena/convert2bids.py
epilepsy2bids/bids/siena/dataset_description.json
epilepsy2bids/bids/siena/eeg.json
epilepsy2bids/bids/siena/participants.json
epilepsy2bids/bids/tuh/README.md
epilepsy2bids/bids/tuh/convert2bids.py
epilepsy2bids/bids/tuh/dataset_description.json
epilepsy2bids/bids/tuh/eeg.json
epilepsy2bids/bids/tuh/participants.json
epilepsy2bids/download/download.py
epilepsy2bids/download/download_seizeit.py
epilepsy2bids/load_annotations/chbmit.py
epilepsy2bids/load_annotations/seizeit.py
epilepsy2bids/load_annotations/siena.py
epilepsy2bids/load_annotations/tuh.py
epilepsy2bids-0.0.7.dist-info/METADATA
epilepsy2bids-0.0.7.dist-info/WHEEL
epilepsy2bids-0.0.7.dist-info/licenses/LICENSE
epilepsy2bids-0.0.7.dist-info/RECORD
