Metadata-Version: 2.3
Name: epilepsy2bids
Version: 0.0.7
Summary: Python library for converting EEG datasets of people with epilepsy to BIDS compatible datasets.
Project-URL: Homepage, https://github.com/esl-epfl/epilepsy2bids
Project-URL: Bug Tracker, https://github.com/esl-epfl/epilepsy2bids/issues
Author: PEDESITE
Author-email: Jonathan Dan <jonathan.dan@epfl.ch>
Classifier: License :: OSI Approved :: MIT License
Classifier: Operating System :: OS Independent
Classifier: Programming Language :: Python :: 3
Requires-Python: >=3.10
Requires-Dist: numpy>=1.24.3
Requires-Dist: pandas>=2.1.3
Requires-Dist: pyarrow>=16.1.0
Requires-Dist: pyedflib>=0.1.36
Requires-Dist: resampy>=0.4.2
Requires-Dist: termcolor>=2.4.0
Requires-Dist: timescoring>=v0.0.5
